django_live_notification/__init__.py
django_live_notification/admin.py
django_live_notification/apps.py
django_live_notification/models.py
django_live_notification/tests.py
django_live_notification/views.py
django_live_notification-0.0.dist-info/LICENSE
django_live_notification-0.0.dist-info/METADATA
django_live_notification-0.0.dist-info/WHEEL
django_live_notification-0.0.dist-info/top_level.txt
django_live_notification-0.0.dist-info/RECORD
